whisper_autosrt/__init__.py
whisper_autosrt-0.1.11.dist-info/METADATA
whisper_autosrt-0.1.11.dist-info/WHEEL
whisper_autosrt-0.1.11.dist-info/entry_points.txt
whisper_autosrt-0.1.11.dist-info/top_level.txt
whisper_autosrt-0.1.11.dist-info/RECORD
